FlaskCasSaml/CasTicketManager.py
FlaskCasSaml/URNmanager.py
FlaskCasSaml/__init__.py
FlaskCasSaml/casSaml_request.py
FlaskCasSaml/cas_response.py
FlaskCasSaml/cas_server.py
FlaskCasSaml/views/__init__.py
FlaskCasSaml/views/base.html
FlaskCasSaml/views/cas_loggedin.html
FlaskCasSaml/views/cas_loggedout.html
FlaskCasSaml/views/v2_auth_failure.xml
FlaskCasSaml/views/v2_auth_success.xml
FlaskCasSaml/views/v2_proxy_failure.xml
FlaskCasSaml/views/v2_proxy_success.xml
FlaskCasSaml/views/v3_cas_saml_error.xml
FlaskCasSaml/views/v3_cas_saml_success.xml
FlaskCasSaml/views/css/__init__.py
FlaskCasSaml/views/css/proj.css
FlaskCasSaml/views/css/spinner.css
FlaskCasSaml-22.3.3.data/data/example/sample_config.py
FlaskCasSaml-22.3.3.data/data/example/sample_flask_cas_saml.py
FlaskCasSaml-22.3.3.dist-info/METADATA
FlaskCasSaml-22.3.3.dist-info/WHEEL
FlaskCasSaml-22.3.3.dist-info/top_level.txt
FlaskCasSaml-22.3.3.dist-info/RECORD
