Metadata-Version: 2.1
Name: FlaskCasSaml
Version: 22.3.3
Summary: Flask-based CAS Server using SAML authentication
Home-page: https://github.com/Glocktober/FlaskCasSaml
Author: gunville
Author-email: rk13088@yahoo.com
License: UNKNOWN
Project-URL: repo, https://github.com/Glocktober/FlaskCasSaml
Project-URL: overview, https://github.com/Glocktober/FlaskCasSaml/blob/master/README.md
Keywords: 'Flask CAS SAML bridge'
Platform: UNKNOWN
Classifier: Programming Language :: Python :: 3
Classifier: License :: OSI Approved :: MIT License
Classifier: Operating System :: OS Independent
Classifier: Framework :: Bottle
Requires-Python: >=3.6
Requires-Dist: Flask
Requires-Dist: Flask-Session
Requires-Dist: defusedxml
Requires-Dist: FlaskSamlSP
Requires-Dist: requests
